<?xml version="1.0" encoding="utf-8"?>
<!--Generated by crowdin.com-->
<!-- Copyright (C) 2019 The Evolution X Project
     Licensed under the Apache License, Version 2.0 (the "License");
     you may not use this file except in compliance with the License.
     You may obtain a copy of the License at
          http://www.apache.org/licenses/LICENSE-2.0
     Unless required by applicable law or agreed to in writing, software
     distributed under the License is distributed on an "AS IS" BASIS,
     WITHOUT WARRANTIES OR CONDITIONS OF ANY KIND, either express or implied.
     See the License for the specific language governing permissions and
     limitations under the License.
-->
<!-- Formatting note: terminate all comments with a period, to avoid breaking
     the documentation output. To suppress comment lines from the documentation
     output, insert an eat-comment element after the comment lines.
-->
<resources>
    <!-- Header. -->
    <string name="text_clock_header_one">Bây giờ là</string>
    <string name="text_clock_header_few">Bây giờ là</string>
    <string name="text_clock_header_multiple">Bây giờ là</string>
    <!-- Hours. -->
    <string name="text_clock_hours_midnight">Nửa đêm</string>
    <string name="text_clock_hours_one">Một giờ</string>
    <string name="text_clock_hours_two">Hai giờ</string>
    <string name="text_clock_hours_three">Ba giờ</string>
    <string name="text_clock_hours_four">Bốn giờ</string>
    <string name="text_clock_hours_five">Năm giờ</string>
    <string name="text_clock_hours_six">Sáu giờ</string>
    <string name="text_clock_hours_seven">Bảy giờ</string>
    <string name="text_clock_hours_eight">Tám giờ</string>
    <string name="text_clock_hours_nine">Chín giờ</string>
    <string name="text_clock_hours_ten">Mười giờ</string>
    <string name="text_clock_hours_eleven">Mười một giờ</string>
    <string name="text_clock_hours_twelve">Mười hai giờ</string>
    <string name="text_clock_hours_thirteen">Mười ba giờ</string>
    <string name="text_clock_hours_fourteen">Mười bốn giờ</string>
    <string name="text_clock_hours_fifteen">Mười lăm giờ</string>
    <string name="text_clock_hours_sixteen">Mười sáu giờ</string>
    <string name="text_clock_hours_seventeen">Mười bảy giờ</string>
    <string name="text_clock_hours_eighteen">Mười tám giờ</string>
    <string name="text_clock_hours_nineteen">Mười chín giờ</string>
    <string name="text_clock_hours_twenty">Hai mươi giờ</string>
    <string name="text_clock_hours_twentyone">Hai mươi mốt giờ</string>
    <string name="text_clock_hours_twentytwo">Hai mươi hai giờ</string>
    <string name="text_clock_hours_twentythree">Hai mươi ba giờ</string>
    <!-- Minutes. -->
    <string name="text_clock_minutes_zero">Không giờ</string>
    <string name="text_clock_minutes_one">Một</string>
    <string name="text_clock_minutes_two">Hai</string>
    <string name="text_clock_minutes_three">Ba</string>
    <string name="text_clock_minutes_four">Bốn</string>
    <string name="text_clock_minutes_five">Năm</string>
    <string name="text_clock_minutes_six">Sáu</string>
    <string name="text_clock_minutes_seven">Bảy</string>
    <string name="text_clock_minutes_eight">Tám</string>
    <string name="text_clock_minutes_nine">Chín</string>
    <string name="text_clock_minutes_ten">Mười</string>
    <string name="text_clock_minutes_eleven">Mười một</string>
    <string name="text_clock_minutes_twelve">Mười hai</string>
    <string name="text_clock_minutes_thirteen">Mười ba</string>
    <string name="text_clock_minutes_fourteen">Mười bốn</string>
    <string name="text_clock_minutes_fifteen">Mười lăm</string>
    <string name="text_clock_minutes_sixteen">Mười sáu</string>
    <string name="text_clock_minutes_seventeen">Mười bảy</string>
    <string name="text_clock_minutes_eighteen">Mười tám</string>
    <string name="text_clock_minutes_nineteen">Mười chín</string>
    <string name="text_clock_minutes_twenty">Hai mươi</string>
    <string name="text_clock_minutes_twentyone">Hai mươi mốt</string>
    <string name="text_clock_minutes_twentytwo">Hai mươi hai</string>
    <string name="text_clock_minutes_twentythree">Hai mươi ba</string>
    <string name="text_clock_minutes_twentyfour">Hai mươi tư</string>
    <string name="text_clock_minutes_twentyfive">Hai mươi lăm</string>
    <string name="text_clock_minutes_twentysix">Hai mươi sáu</string>
    <string name="text_clock_minutes_twentyseven">Hai mươi bảy</string>
    <string name="text_clock_minutes_twentyeight">Hai mươi tám</string>
    <string name="text_clock_minutes_twentynine">Hai mươi chín</string>
    <string name="text_clock_minutes_thirty">Ba mươi</string>
    <string name="text_clock_minutes_thirtyone">Ba mươi mốt</string>
    <string name="text_clock_minutes_thirtytwo">Ba mươi hai</string>
    <string name="text_clock_minutes_thirtythree">Ba mươi ba</string>
    <string name="text_clock_minutes_thirtyfour">Ba mươi bốn</string>
    <string name="text_clock_minutes_thirtyfive">Ba mươi lăm</string>
    <string name="text_clock_minutes_thirtysix">Ba mươi sáu</string>
    <string name="text_clock_minutes_thirtyseven">Ba mươi bảy</string>
    <string name="text_clock_minutes_thirtyeight">Ba mươi tám</string>
    <string name="text_clock_minutes_thirtynine">Ba mươi chín</string>
    <string name="text_clock_minutes_fifty">Năm mươi</string>
    <string name="text_clock_minutes_fiftyone">Năm mươi mốt</string>
    <string name="text_clock_minutes_fiftytwo">Năm mươi hai</string>
    <string name="text_clock_minutes_fiftythree">Năm mươi ba</string>
    <string name="text_clock_minutes_fiftyfour">Năm mươi bốn</string>
    <string name="text_clock_minutes_fiftyfive">Năm mươi lăm</string>
    <string name="text_clock_minutes_fiftysix">Năm mươi sáu</string>
    <string name="text_clock_minutes_fiftyseven">Năm mươi bảy</string>
    <string name="text_clock_minutes_fiftyeight">Năm mươi tám</string>
    <string name="text_clock_minutes_fiftynine">Năm mươi chín</string>
</resources>
